golfdb/__init__.py
golfdb/model.py
golfdb/cli/__init__.py
golfdb/cli/dev.py
golfdb/migration/__init__.py
golfdb/migration/migration_2024_08_13_13_32_45_b7404a13955b_0_1_0.py
golfdb-0.1.0.dist-info/LICENSE
golfdb-0.1.0.dist-info/METADATA
golfdb-0.1.0.dist-info/WHEEL
golfdb-0.1.0.dist-info/entry_points.txt
golfdb-0.1.0.dist-info/top_level.txt
golfdb-0.1.0.dist-info/RECORD
